tuze_python_sdk/__init__.py
tuze_python_sdk/http_util.py
tuze_python_sdk-1.1.0.dist-info/METADATA
tuze_python_sdk-1.1.0.dist-info/WHEEL
tuze_python_sdk-1.1.0.dist-info/top_level.txt
tuze_python_sdk-1.1.0.dist-info/RECORD
