Metadata-Version: 2.1
Name: tuze_python_sdk
Version: 1.1.0
Summary: python sdk for tuze platform
Author-email: tuze <sharkshore@163.com>
License: MIT
Project-URL: Homepage, https://github.com/sharkshore/python-base-sample
Classifier: Programming Language :: Python :: 3
Classifier: License :: OSI Approved :: MIT License
Classifier: Operating System :: OS Independent
Requires-Python: >=3.6
Requires-Dist: requests
Requires-Dist: colorama
